onegov.search-1.7.0-py3.6-nspkg.pth
onegov/search/.gitignore
onegov/search/__init__.py
onegov/search/cli.py
onegov/search/dsl.py
onegov/search/errors.py
onegov/search/indexer.py
onegov/search/integration.py
onegov/search/mixins.py
onegov/search/upgrade.py
onegov/search/utils.py
onegov/search/tests/conftest.py
onegov/search/tests/test_indexer.py
onegov/search/tests/test_integration.py
onegov/search/tests/test_utils.py
onegov.search-1.7.0.dist-info/METADATA
onegov.search-1.7.0.dist-info/WHEEL
onegov.search-1.7.0.dist-info/entry_points.txt
onegov.search-1.7.0.dist-info/namespace_packages.txt
onegov.search-1.7.0.dist-info/top_level.txt
onegov.search-1.7.0.dist-info/RECORD
