Metadata-Version: 2.1
Name: onegov.search
Version: 1.7.0
Summary: Elasticsearch integration for OneGov Cloud
Home-page: http://github.com/OneGov/onegov.search
Author: Seantis GmbH
Author-email: info@seantis.ch
License: GPLv2
Platform: any
Classifier: Intended Audience :: Developers
Classifier: Programming Language :: Python :: 3 :: Only
Classifier: Programming Language :: Python :: 3.6
Classifier: Programming Language :: Python :: 3.7
Classifier: Topic :: Software Development :: Libraries :: Python Modules
Classifier: License :: OSI Approved :: GNU General Public License v2 (GPLv2)
Requires-Python: >=3.6
Requires-Dist: certifi
Requires-Dist: elasticsearch (<7.0.0,>=6.0.0)
Requires-Dist: elasticsearch-dsl (<7.0.0,>=6.0.0)
Requires-Dist: langdetect
Requires-Dist: onegov.core (>=0.22.0)
Requires-Dist: sortedcontainers
Requires-Dist: webtest
Provides-Extra: test
Requires-Dist: coverage ; extra == 'test'
Requires-Dist: onegov-testing ; extra == 'test'
Requires-Dist: sqlalchemy ; extra == 'test'
Requires-Dist: pytest ; extra == 'test'
